Workbook

Sheet Liquor
A2: Size . | B2: OZ | C2: Name | D2: Type | E2: Bottle Cost | F2: Cost Per OZ | G2: Cost 1.5oz | H2: Menu $ | I2: Cost% | J2: Main Bar | K2: Pool Bar | L2: Liquor Room | M2: Total | N2: Total Value
A3: Bitters | B3: 4 | C3: Angostura Bitters | D3: bitters | E3: 13.13 | F3: =E3/$B9 -> 0.820625 | G3: =Liquor!$F3*1.5 -> 1.2309375 | H3: 8 | I3: =Liquor!$G3/Liquor!$H3 -> 0.15386719 | M3: =SUM(Liquor!$J3:$L3) -> 0 | N3: =$M3*$E3 -> 0
A4: Bitters | B4: 4 | C4: Angostura Bitters orange | D4: bitters | E4: 8.04 | F4: =E4/$B9 -> 0.5025 | G4: =Liquor!$F4*1.5 -> 0.75375 | H4: 5 | I4: =Liquor!$G4/Liquor!$H4 -> 0.15075 | M4: =SUM(Liquor!$J4:$L4) -> 0 | N4: =$M4*$E4 -> 0
A5: Bitters | B5: 6.7 | C5: Angostura Bitters orange | D5: bitters | E5: 16.99 | F5: =E5/$B9 -> 1.061875 | G5: =Liquor!$F5*1.5 -> 1.5928125 | H5: 15 | I5: =Liquor!$G5/Liquor!$H5 -> 0.1061875 | M5: =SUM(Liquor!$J5:$L5) -> 0 | N5: =$M5*$E5 -> 0
A6: Bitters | B6: 5 | C6: Fee Brother Rhubarb bitters | D6: bitters | E6: 9.43 | F6: =E6/$B10 -> 1.886 | G6: =Liquor!$F6*1.5 -> 2.829 | H6: 18 | I6: =Liquor!$G6/Liquor!$H6 -> 0.15716667 | M6: =SUM(Liquor!$J6:$L6) -> 0 | N6: =$M6*$E6 -> 0
A7: Bitters | B7: 5 | C7: Scrappy Lemon Bitters | D7: bitters | E7: 19.89 | F7: =E7/$B10 -> 3.978 | G7: =Liquor!$F7*1.5 -> 5.967 | H7: 38 | I7: =Liquor!$G7/Liquor!$H7 -> 0.15702632 | M7: =SUM(Liquor!$J7:$L7) -> 0 | N7: =$M7*$E7 -> 0
A8: Bitters | B8: 5 | C8: Fee Brother Black Walnut Bitters | D8: bitters | E8: 9.43 | F8: =E8/$B11 -> 1.886 | G8: =Liquor!$F8*1.5 -> 2.829 | H8: 18 | I8: =Liquor!$G8/Liquor!$H8 -> 0.15716667 | M8: =SUM(Liquor!$J8:$L8) -> 0 | N8: =$M8*$E8 -> 0
A9: Bitters | B9: 16 | C9: Angostura Bitters | D9: bitters | E9: 27.6 | F9: =$E9/$B9 -> 1.725 | G9: =Liquor!$F9*1.5 -> 2.5875 | H9: 18 | I9: =Liquor!$G9/Liquor!$H9 -> 0.14375 | M9: =SUM(Liquor!$J9:$L9)+$K409 -> 0 | N9: =$M9*$E9 -> 0
A10: Bitters | B10: 5 | C10: Bittermans Hopped Grapefruit Bitters | D10: bitters | E10: 17.7 | F10: =$E10/$B10 -> 3.54 | G10: =Liquor!$F10*1.5 -> 5.31 | H10: 32 | I10: =Liquor!$G10/Liquor!$H10 -> 0.1659375 | M10: 0 | N10: =$M10*$E10 -> 0
A11: Bitters | B11: 5 | C11: Bittermans Xocolatl Mole Bitters | D11: bitters | E11: 17.25 | F11: =$E11/$B11 -> 3.45 | G11: =Liquor!$F11*1.5 -> 5.175 | H11: 32 | I11: =Liquor!$G11/Liquor!$H11 -> 0.16171875 | M11: =SUM(Liquor!$J11:$L11) -> 0 | N11: =$M11*$E11 -> 0
A12: Bitters | B12: 5 | C12: Peychaud Bitters | D12: bitters | E12: 5.4 | F12: =$E12/$B12 -> 1.08 | G12: =Liquor!$F12*1.5 -> 1.62 | H12: 15 | I12: =Liquor!$G12/Liquor!$H12 -> 0.108 | M12: =SUM(Liquor!$J12:$L12) -> 0 | N12: =$M12*$E12 -> 0
A13: Bitters | B13: 5 | C13: Fee Brother chocolate Aztec bitters | D13: bitters | E13: 8.7 | F13: =$E13/$B13 -> 1.74 | G13: =Liquor!$F13*1.5 -> 2.61 | H13: 15 | I13: =Liquor!$G13/Liquor!$H13 -> 0.174 | M13: =SUM(Liquor!$J13:$L13)+$K405 -> 0 | N13: =$M13*$E13 -> 0
A14: Bitters | B14: 5 | C14: Fee Brother Bitter Orange | D14: bitters | E14: 9.43 | F14: =$E14/$B14 -> 1.886 | G14: =Liquor!$F14*1.5 -> 2.829 | H14: 15 | I14: =Liquor!$G14/Liquor!$H14 -> 0.1886 | M14: =SUM(Liquor!$J14:$L14) -> 0 | N14: =$M14*$E14 -> 0
A15: Bitters | B15: 5 | C15: Fee Brother Mint Bitters | D15: bitters | E15: 9.43 | F15: =$E15/$B15 -> 1.886 | G15: =Liquor!$F15*1.5 -> 2.829 | H15: 25 | I15: =Liquor!$G15/Liquor!$H15 -> 0.11316 | M15: =SUM(Liquor!$J15:$L15) -> 0 | N15: =$M15*$E15 -> 0
A16: Bitters | B16: 5 | C16: Fee Brother Celery Bitters | D16: bitters | E16: 8.84 | F16: =$E16/$B16 -> 1.768 | G16: =Liquor!$F16*1.5 -> 2.652 | H16: 25 | I16: =Liquor!$G16/Liquor!$H16 -> 0.10608 | M16: =SUM(Liquor!$J16:$L16)+$K447 -> 0 | N16: =$M16*$E16 -> 0
A17: Bitters | B17: 5 | C17: Fee Brother Cherry Bitters | D17: bitters | E17: 8.7 | F17: =$E17/$B17 -> 1.74 | G17: =Liquor!$F17*1.5 -> 2.61 | H17: 25 | I17: =Liquor!$G17/Liquor!$H17 -> 0.1044 | M17: =SUM(Liquor!$J17:$L17) -> 0 | N17: =$M17*$E17 -> 0
A18: Bitters | B18: 3.38 | C18: Greenbar Apple Bitters | D18: bitters | E18: 9.69 | F18: =$E18/$B18 -> 2.8668639 | G18: =Liquor!$F18*1.5 -> 4.3002959 | H18: 25 | I18: =Liquor!$G18/Liquor!$H18 -> 0.17201183 | M18: =SUM(Liquor!$J18:$L18) -> 0 | N18: =$M18*$E18 -> 0
A19: Bitters | B19: 5 | C19: Scrappy's Lavender Bitters | D19: bitters | E19: 19.89 | F19: =$E19/$B19 -> 3.978 | G19: =Liquor!$F19*1.5 -> 5.967 | H19: 35 | I19: =Liquor!$G19/Liquor!$H19 -> 0.17048571 | M19: =SUM(Liquor!$J19:$L19) -> 0 | N19: =$M19*$E19 -> 0
A20: Bitters | B20: 5 | C20: Scrappy's Cardamon Bitters | D20: bitters | E20: 20.51 | F20: =$E20/$B20 -> 4.102 | G20: =Liquor!$F20*1.5 -> 6.153 | H20: 40 | I20: =Liquor!$G20/Liquor!$H20 -> 0.153825 | M20: =SUM(Liquor!$J20:$L20) -> 0 | N20: =$M20*$E20 -> 0
A21: Bitters | B21: 5 | C21: El Guapo Chicory Pecan Bitters | D21: bitters | E21: 16.42 | F21: =$E21/$B21 -> 3.284 | G21: =Liquor!$F21*1.5 -> 4.926 | H21: 35 | I21: =Liquor!$G21/Liquor!$H21 -> 0.14074286 | M21: =SUM(Liquor!$J21:$L21) -> 0 | N21: =$M21*$E21 -> 0
A22: Quart | B22: 32 | C22: Lime Juice (1qrt) | D22: Juice | E22: 5.1 | F22: =$E22/$B22 -> 0.159375 | G22: =Liquor!$F22*1.5 -> 0.2390625 | H22: 4 | I22: =Liquor!$G22/Liquor!$H22 -> 0.059765625 | M22: =SUM(Liquor!$J22:$L22) -> 0 | N22: =$M22*$E22 -> 0
A23: Quart | B23: 32 | C23: Lemon Juice (1qrt) | D23: juice | E23: 5.1 | F23: =$E23/$B23 -> 0.159375 | G23: =Liquor!$F23*1.5 -> 0.2390625 | H23: 4 | I23: =Liquor!$G23/Liquor!$H23 -> 0.059765625 | M23: =SUM(Liquor!$J23:$L23) -> 0 | N23: =$M23*$E23 -> 0
A24: Gallon | B24: 128 | C24: Orange Juice (1gal) | D24: juice | E24: 15.3 | F24: =$E24/$B24 -> 0.11953125 | G24: =Liquor!$F24*1.5 -> 0.17929688 | H24: 4 | I24: =Liquor!$G24/Liquor!$H24 -> 0.044824219 | M24: =SUM(Liquor!$J24:$L24) -> 0 | N24: =$M24*$E24 -> 0
B25: 16 | C25: Pineapple Juice (48oz) | D25: juice | E25: 3.84 | F25: =$E25/$B25 -> 0.24 | G25: =Liquor!$F25*1.5 -> 0.36 | H25: 4 | I25: =Liquor!$G25/Liquor!$H25 -> 0.09 | M25: =SUM(Liquor!$J25:$L25) -> 0 | N25: =$M25*$E25 -> 0
B26: 64 | C26: Cranberry Juice | D26: juice | E26: 3.53 | F26: =$E26/$B26 -> 0.05515625 | G26: =Liquor!$F26*1.5 -> 0.082734375 | H26: 4 | I26: =Liquor!$G26/Liquor!$H26 -> 0.020683594 | M26: =SUM(Liquor!$J26:$L26) -> 0 | N26: =$M26*$E26 -> 0
B27: 64 | C27: Grapefruit Juice | D27: juice | E27: 3.45 | F27: =$E27/$B27 -> 0.05390625 | G27: =Liquor!$F27*1.5 -> 0.080859375 | H27: 4 | I27: =Liquor!$G27/Liquor!$H27 -> 0.020214844 | M27: =SUM(Liquor!$J27:$L27) -> 0 | N27: =$M27*$E27 -> 0
B28: 16 | C28: Blood Orange Juice | D28: juice | E28: 3.32 | F28: =$E28/$B28 -> 0.2075 | G28: =Liquor!$F28*1.5 -> 0.31125 | H28: 4 | I28: =Liquor!$G28/Liquor!$H28 -> 0.0778125 | M28: =SUM(Liquor!$J28:$L28) -> 0 | N28: =$M28*$E28 -> 0
A29: 1 Liter | B29: 33.814 | C29: Coco Loco | D29: batch | E29: 2.82 | F29: =$E29/$B29 -> 0.083397409 | G29: =Liquor!$F29*1.5 -> 0.12509611 | H29: 1 | I29: =Liquor!$G29/Liquor!$H29 -> 0.12509611 | M29: =SUM(Liquor!$J29:$L29) -> 0 | N29: =$M29*$E29 -> 0
A30: 1 Liter | B30: 33.814 | C30: Boiron Frozen Blood Orange Puree | D30: puree | E30: 18.95 | F30: =$E30/$B30 -> 0.56041876 | G30: =Liquor!$F30*1.5 -> 0.84062814 | H30: 5 | I30: =Liquor!$G30/Liquor!$H30 -> 0.16812563 | M30: =SUM(Liquor!$J30:$L30)+$I414 -> 0 | N30: =$M30*$E30 -> 0
A31: 1 Liter | B31: 33.814 | C31: Boiron Guava Puree | D31: puree | E31: 18.95 | F31: =$E31/$B31 -> 0.56041876 | G31: =Liquor!$F31*1.5 -> 0.84062814 | H31: 5 | I31: =Liquor!$G31/Liquor!$H31 -> 0.16812563 | M31: =SUM(Liquor!$J31:$L31) -> 0 | N31: =$M31*$E31 -> 0
A32: 1 Liter | B32: 33.814 | C32: Finest Call Strawberry Puree | D32: puree | E32: 5.2 | F32: =$E32/$B32 -> 0.15378246 | G32: =Liquor!$F32*1.5 -> 0.23067369 | H32: 7 | I32: =Liquor!$G32/Liquor!$H32 -> 0.032953384 | M32: =SUM(Liquor!$J32:$L32) -> 0 | N32: =$M32*$E32 -> 0
A33: 1 Liter | B33: 33.814 | C33: Rose's Grenadine | D33: mixer | E33: 6.89 | F33: =$E33/$B33 -> 0.20376176 | G33: =Liquor!$F33*1.5 -> 0.30564263 | H33: 8 | I33: =Liquor!$G33/Liquor!$H33 -> 0.038205329 | M33: =SUM(Liquor!$J33:$L33) -> 0 | N33: =$M33*$E33 -> 0
B34: 8 | C34: Filthy Olive Juice | D34: mixer | E34: 4.1 | F34: =$E34/$B34 -> 0.5125 | G34: =Liquor!$F34*1.5 -> 0.76875 | H34: 2 | I34: =Liquor!$G34/Liquor!$H34 -> 0.384375 | M34: =SUM(Liquor!$J34:$L34) -> 0 | N34: =$M34*$E34 -> 0
A35: 1.75 Liter | B35: 59.17 | C35: Zing Zang Bloody Mary Mix | D35: mixer | E35: 9.9 | F35: =$E35/$B35 -> 0.16731452 | G35: =Liquor!$F35*1.5 -> 0.25097178 | H35: 8 | I35: =Liquor!$G35/Liquor!$H35 -> 0.031371472 | M35: =SUM(Liquor!$J35:$L35) -> 0 | N35: =$M35*$E35 -> 0
B36: 33.814 | C36: Zing Zang Bloody Mary Mix | D36: syrup | E36: 11.66 | F36: =$E36/$B36 -> 0.34482759 | G36: =Liquor!$F36*1.5 -> 0.51724138 | H36: 8 | I36: =Liquor!$G36/Liquor!$H36 -> 0.064655172 | M36: =SUM(Liquor!$J36:$L36) -> 0 | N36: =$M36*$E36 -> 0
A37: 750ml | B37: 25.36 | C37: Liber Fig Syrup | D37: syrup | E37: 18 | F37: =$E37/$B37 -> 0.70977918 | G37: =Liquor!$F37*1.5 -> 1.0646688 | M37: =SUM(Liquor!$J37:$L37) -> 0 | N37: =$M37*$E37 -> 0
A38: 750ml | B38: 25.36 | C38: Liber Raspberry Gum Syrup | D38: syrup | E38: 17.13 | F38: =$E38/$B38 -> 0.67547319 | G38: =Liquor!$F38*1.5 -> 1.0132098 | M38: =SUM(Liquor!$J38:$L38) -> 0 | N38: =$M38*$E38 -> 0
A39: 1 Liter | B39: 33.814 | C39: Monin Agave | D39: syrup | E39: 11.26 | F39: =$E39/$B39 -> 0.33299817 | G39: =Liquor!$F39*1.5 -> 0.49949725 | H39: 8 | I39: =Liquor!$G39/Liquor!$H39 -> 0.062437156 | M39: =SUM(Liquor!$J39:$L39) -> 0 | N39: =$M39*$E39 -> 0
A40: 750ml | B40: 25.36 | C40: Giffard Orgeat | D40: syrup | E40: 20.86 | F40: =$E40/$B40 -> 0.82255521 | G40: =Liquor!$F40*1.5 -> 1.2338328 | H40: 8 | I40: =Liquor!$G40/Liquor!$H40 -> 0.1542291 | M40: =SUM(Liquor!$J40:$L40) -> 0 | N40: =$M40*$E40 -> 0
A41: 750ml | B41: 25.36 | C41: Seedlip 108 | D41: n/a | E41: 26.16 | F41: =$E41/$B41 -> 1.0315457 | G41: =Liquor!$F41*1.5 -> 1.5473186 | H41: 12 | I41: =Liquor!$G41/Liquor!$H41 -> 0.12894322 | M41: =SUM(Liquor!$J41:$L41) -> 0 | N41: =$M41*$E41 -> 0
A42: 750ml | B42: 25.36 | C42: Kentucky 74 whiskey | D42: n/a | E42: 29.42 | F42: =$E42/$B42 -> 1.1600946 | G42: =Liquor!$F42*1.5 -> 1.740142 | H42: 12 | I42: =Liquor!$G42/Liquor!$H42 -> 0.14501183 | M42: =SUM(Liquor!$J42:$L42) -> 0 | N42: =$M42*$E42 -> 0
A43: 750ml | B43: 25.36 | C43: Jalisco 55 | D43: n/a | E43: 28.6 | F43: =$E43/$B43 -> 1.1277603 | G43: =Liquor!$F43*1.5 -> 1.6916404 | H43: 12 | I43: =Liquor!$G43/Liquor!$H43 -> 0.14097003 | M43: =SUM(Liquor!$J43:$L43) -> 0 | N43: =$M43*$E43 -> 0
A44: 750ml | B44: 25.36 | C44: Brez | D44: n/a | E44: 41.367 | F44: =$E44/$B44 -> 1.6311909 | G44: =Liquor!$F44*1.5 -> 2.4467863 | H44: 12 | I44: =Liquor!$G44/Liquor!$H44 -> 0.20389886 | M44: =SUM(Liquor!$J44:$L44) -> 0 | N44: =$M44*$E44 -> 0
B45: 12 | C45: Brez Flow | D45: n/a | E45: 2.79 | F45: =$E45/$B45 -> 0.2325 | G45: =Liquor!$F45*1.5 -> 0.34875 | H45: 7 | I45: =Liquor!$G45/Liquor!$H45 -> 0.049821429 | M45: =SUM(Liquor!$J45:$L45) -> 0 | N45: =$M45*$E45 -> 0
B46: 7 | C46: Brez THC | D46: n/a thc | E46: 2.79 | F46: =$E46/$B46 -> 0.39857143 | G46: =Liquor!$F46*1.5 -> 0.59785714 | H46: 8 | I46: =Liquor!$G46/Liquor!$H46 -> 0.074732143 | M46: =SUM(Liquor!$J46:$L46) -> 0 | N46: =$M46*$E46 -> 0
A47: 750ml | B47: 25.36 | C47: Giffard Ginger Liqueur NA | D47: n/a | E47: 23.43 | F47: =$E47/$B47 -> 0.9238959 | G47: =Liquor!$F47*1.5 -> 1.3858438 | H47: 12 | I47: =Liquor!$G47/Liquor!$H47 -> 0.11548699 | M47: =SUM(Liquor!$J47:$L47) -> 0 | N47: =$M47*$E47 -> 0
B48: 5.95 | C48: Crodino NA Spritz | D48: n/a | E48: 3 | F48: =$E48/$B48 -> 0.50420168 | G48: =Liquor!$F48*1.5 -> 0.75630252 | H48: 10 | I48: =Liquor!$E48/Liquor!$H48 -> 0.3 | L48: =48+20 -> 68 | M48: =SUM(Liquor!$J48:$L48) -> 68 | N48: =$M48*$E40 -> 1418.48
C49: Dehy Orange | D49: garnish | E49: 55 | M49: =SUM(Liquor!$J49:$L49) -> 0 | N49: =$M49*$E42 -> 0
C50: Dehy Lemon | D50: garnish | E50: 55 | M50: =SUM(Liquor!$J50:$L50) -> 0 | N50: =$M50*$E43 -> 0
C51: Dehy Lime | D51: garnish | E51: 55 | M51: =SUM(Liquor!$J51:$L51) -> 0 | N51: =$M51*$E44 -> 0
C52: Olives | D52: garnish | E52: 26.15 | M52: =SUM(Liquor!$J52:$L52) -> 0 | N52: =$M52*$E40 -> 0
C53: Cocktail Onions | D53: garnish | E53: 2.56 | M53: =SUM(Liquor!$J53:$L53) -> 0 | N53: =$M53*$E53 -> 0
B54: 64 | C54: Filthy Blue Cheese Olives | D54: garnish | E54: 34.8 | M54: =SUM(Liquor!$J54:$L54) -> 0 | N54: =$M54*$E54 -> 0
C55: Luxardo Cherries 3kg | D55: garnish | E55: 94.95 | M55: =SUM(Liquor!$J55:$L55) -> 0 | N55: =$M55*$E55 -> 0
C56: Fat Ice 2x2 | D56: ice | E56: 65 | L56: 3 | M56: =SUM(Liquor!$J56:$L56) -> 3 | N56: =$M56*$E56 -> 195
C57: Fat Ice Collins | D57: ice | E57: 80.75 | M57: =SUM(Liquor!$J57:$L57) -> 0 | N57: =$M57*$E57 -> 0
A58: 750ml | B58: 25.36 | C58: Abasolo whiskey | D58: whiskey | E58: 37.06 | F58: =$E58/$B58 -> 1.4613565 | G58: =Liquor!$F58*1.5 -> 2.1920347 | H58: 13 | I58: =Liquor!$G58/Liquor!$H58 -> 0.16861805 | J58: 0.85 | M58: =SUM(Liquor!$J58:$L58) -> 0.85 | N58: =$M58*$E58 -> 31.501
A59: 1 Liter | B59: 33.814 | C59: Angel's Envy Bourbon | D59: bourbon | E59: 45.48 | F59: =$E59/$B59 -> 1.345005 | G59: =Liquor!$F59*1.5 -> 2.0175075 | H59: 16 | I59: =Liquor!$G59/Liquor!$H59 -> 0.12609422 | J59: 0.6 | M59: =SUM(Liquor!$J59:$L59) -> 0.6 | N59: =$M59*$E59 -> 27.288
A60: 750ml | B60: 25.36 | C60: Balcones Texas Single Malt | D60: bourbon | E60: 47.83 | F60: =$E60/$B60 -> 1.886041 | G60: =Liquor!$F60*1.5 -> 2.8290615 | H60: 16 | I60: =Liquor!$G60/Liquor!$H60 -> 0.17681634 | M60: =SUM(Liquor!$J60:$L60) -> 0 | N60: =$M60*$E60 -> 0
A61: 1 Liter | B61: 33.814 | C61: Basil Hayden Bourbon | D61: bourbon | E61: 49.12 | F61: =$E61/$B61 -> 1.4526527 | G61: =Liquor!$F61*1.5 -> 2.1789791 | H61: 15 | I61: =Liquor!$G61/Liquor!$H61 -> 0.14526527 | J61: 0.25 | M61: =SUM(Liquor!$J61:$L61) -> 0.25 | N61: =$M61*$E61 -> 12.28
A62: 750ml | B62: 25.36 | C62: Basil Hayden Bourbon | D62: bourbon | E62: 41.08 | F62: =$E62/$B62 -> 1.6198738 | G62: =Liquor!$F62*1.5 -> 2.4298107 | H62: 15 | I62: =Liquor!$G62/Liquor!$H62 -> 0.16198738 | M62: =SUM(Liquor!$J62:$L62) -> 0 | N62: =$M62*$E62 -> 0
A63: 750ml | B63: 25.36 | C63: Basil Hayden Dark Rye | D63: rye | E63: 38.86 | F63: =$E63/$B63 -> 1.5323344 | G63: =Liquor!$F63*1.5 -> 2.2985016 | H63: 17 | I63: =Liquor!$G63/Liquor!$H63 -> 0.13520598 | J63: 0.5 | M63: =SUM(Liquor!$J63:$L63) -> 0.5 | N63: =$M63*$E63 -> 19.43
A64: 750ml | B64: 25.36 | C64: Blanton's Bourbon | D64: bourbon | E64: 66.24 | F64: =$E64/$B64 -> 2.6119874 | G64: =Liquor!$F64*1.5 -> 3.9179811 | H64: 22 | I64: =Liquor!$G64/Liquor!$H64 -> 0.17809005 | J64: 0.65 | M64: =SUM(Liquor!$J64:$L64) -> 0.65 | N64: =$M64*$E64 -> 43.056
A65: 750ml | B65: 25.36 | C65: Buffalo Trace Bourbon | D65: bourbon | E65: 22.75 | F65: =$E65/$B65 -> 0.89708202 | G65: =Liquor!$F65*1.5 -> 1.345623 | H65: 12 | I65: =Liquor!$G65/Liquor!$H65 -> 0.11213525 | M65: =SUM(Liquor!$J65:$L65) -> 0 | N65: =$M65*$E65 -> 0
A66: 1 Liter | B66: 33.814 | C66: Buffalo Trace Bourbon | D66: bourbon | E66: 26.38 | F66: =$E66/$B66 -> 0.78015023 | G66: =Liquor!$F66*1.5 -> 1.1702254 | H66: 12 | I66: =Liquor!$G66/Liquor!$H66 -> 0.097518779 | J66: 0.3 | M66: =SUM(Liquor!$J66:$L66) -> 0.3 | N66: =$M66*$E66 -> 7.914
A67: 750ml | B67: 25.36 | C67: Bulleit Bourbon | D67: bourbon | E67: 27.36 | F67: =$E67/$B67 -> 1.0788644 | G67: =Liquor!$F67*1.5 -> 1.6182965 | H67: 12 | I67: =Liquor!$G67/Liquor!$H67 -> 0.13485804 | M67: =SUM(Liquor!$J67:$L67) -> 0 | N67: =$M67*$E67 -> 0
A68: 1 Liter | B68: 33.814 | C68: Bulleit Bourbon | D68: bourbon | E68: 31.59 | F68: =$E68/$B68 -> 0.93422843 | G68: =Liquor!$F68*1.5 -> 1.4013426 | H68: 12 | I68: =Liquor!$G68/Liquor!$H68 -> 0.11677855 | M68: =SUM(Liquor!$J68:$L68) -> 0 | N68: =$M68*$E68 -> 0
A69: 1 Liter | B69: 33.814 | C69: Bulleit Rye | D69: rye | E69: 31.59 | F69: =$E69/$B69 -> 0.93422843 | G69: =Liquor!$F69*1.5 -> 1.4013426 | H69: 14 | I69: =Liquor!$G69/Liquor!$H69 -> 0.1000959 | J69: 0.3 | M69: =SUM(Liquor!$J69:$L69) -> 0.3 | N69: =$M69*$E69 -> 9.477
A70: 750ml | B70: 25.36 | C70: Bespoken Twice Toasted Bourbon Whiskey | D70: whiskey | E70: 36.79 | F70: =$E70/$B70 -> 1.4507098 | G70: =Liquor!$F70*1.5 -> 2.1760647 | H70: 14 | I70: =Liquor!$G70/Liquor!$H70 -> 0.15543319 | J70: 0.1 | M70: =SUM(Liquor!$J70:$L70) -> 0.1 | N70: =$M70*$E70 -> 3.679
A71: 750ml | B71: 25.36 | C71: Bespoken Twice Toasted American Whiskey | D71: whiskey | E71: 33.75 | F71: =$E71/$B71 -> 1.330836 | G71: =Liquor!$F71*1.5 -> 1.9962539 | H71: 14 | I71: =Liquor!$G71/Liquor!$H71 -> 0.14258957 | J71: 0.15 | M71: =SUM(Liquor!$J71:$L71) -> 0.15 | N71: =$M71*$E71 -> 5.0625
A72: 1 Liter | B72: 33.814 | C72: Crown Royal | D72: whisky | E72: 33.2 | F72: =$E72/$B72 -> 0.98184184 | G72: =Liquor!$F72*1.5 -> 1.4727628 | H72: 12 | I72: =Liquor!$G72/Liquor!$H72 -> 0.12273023 | J72: 0.75 | M72: =SUM(Liquor!$J72:$L72) -> 0.75 | N72: =$M72*$E72 -> 24.9
A73: 750ml | B73: 25.36 | C73: Eagle Rare 10Y | D73: bourbon | E73: 33.32 | F73: =$E73/$B73 -> 1.3138801 | G73: =Liquor!$F73*1.5 -> 1.9708202 | H73: 16 | I73: =Liquor!$G73/Liquor!$H73 -> 0.12317626 | J73: 0.5 | M73: =SUM(Liquor!$J73:$L73) -> 0.5 | N73: =$M73*$E73 -> 16.66
A74: 750ml | B74: 25.36 | C74: E.H. Taylor Barrel Proof | D74: bourbon | E74: 64.61 | F74: =$E74/$B74 -> 2.5477129 | G74: =Liquor!$F74*1.5 -> 3.8215694 | H74: 24 | I74: =Liquor!$G74/Liquor!$H74 -> 0.15923206 | J74: 0.25 | M74: =SUM(Liquor!$J74:$L74) -> 0.25 | N74: =$M74*$E74 -> 16.1525
A75: 750ml | B75: 25.36 | C75: E.H. Taylor Single Barrel | D75: bourbon | E75: 44.81 | F75: =$E75/$B75 -> 1.7669558 | G75: =Liquor!$F75*1.5 -> 2.6504338 | H75: 18 | I75: =Liquor!$G75/Liquor!$H75 -> 0.14724632 | J75: 0.1 | M75: =SUM(Liquor!$J75:$L75) -> 0.1 | N75: =$M75*$E75 -> 4.481
A76: 1 Liter | B76: 33.814 | C76: Four Roses Bourbon | D76: bourbon | E76: 16.85 | F76: =$E76/$B76 -> 0.49831431 | G76: =Liquor!$F76*1.5 -> 0.74747146 | H76: 10 | I76: =Liquor!$G76/Liquor!$H76 -> 0.074747146 | J76: 0.9 | M76: =SUM(Liquor!$J76:$L76)+$J408 -> 0.9 | N76: =$M76*$E76 -> 15.165
A77: 750ml | B77: 25.36 | C77: Frey Ranch Bourbon | D77: bourbon | E77: 45.11 | F77: =$E77/$B77 -> 1.7787855 | G77: =Liquor!$F77*1.5 -> 2.6681782 | H77: 17 | I77: =Liquor!$G77/Liquor!$H77 -> 0.15695166 | J77: 0.5 | M77: =SUM(Liquor!$J77:$L77) -> 0.5 | N77: =$M77*$E77 -> 22.555
A78: 750ml | B78: 25.36 | C78: Garrison Brothers Bourbon | D78: bourbon | E78: 64.4 | F78: =$E78/$B78 -> 2.5394322 | G78: =Liquor!$F78*1.5 -> 3.8091483 | H78: 21 | I78: =Liquor!$G78/Liquor!$H78 -> 0.18138801 | J78: 0.1 | M78: =SUM(Liquor!$J78:$L78) -> 0.1 | N78: =$M78*$E78 -> 6.44
A79: 750ml | B79: 25.36 | C79: Garrison Brothers Single Barrel | D79: bourbon | E79: 87.89 | F79: =$E79/$B79 -> 3.465694 | G79: =Liquor!$F79*1.5 -> 5.198541 | H79: 25 | I79: =Liquor!$G79/Liquor!$H79 -> 0.20794164 | M79: =SUM(Liquor!$J79:$L79) -> 0 | N79: =$M79*$E79 -> 0
A80: 750ml | B80: 25.36 | C80: Hibiki Japanese Harmony | D80: whisky | E80: 83.62 | F80: =$E80/$B80 -> 3.2973186 | G80: =Liquor!$F80*1.5 -> 4.9459779 | H80: 28 | I80: =Liquor!$G80/Liquor!$H80 -> 0.17664207 | J80: 0.6 | M80: =SUM(Liquor!$J80:$L80) -> 0.6 | N80: =$M80*$E80 -> 50.172
A81: 750ml | B81: 25.36 | C81: Hakushu 12Y | D81: whisky | E81: 149.92 | F81: =$E81/$B81 -> 5.9116719 | G81: =Liquor!$F81*1.5 -> 8.8675079 | H81: 38 | I81: =Liquor!$G81/Liquor!$H81 -> 0.23335547 | J81: 1.1 | M81: =SUM(Liquor!$J81:$L81) -> 1.1 | N81: =$M81*$E81 -> 164.912
A82: 750ml | B82: 25.36 | C82: Jack Daniels Old No. 7 Whiskey | D82: whiskey | E82: 23.38 | F82: =$E82/$B82 -> 0.92192429 | G82: =Liquor!$F82*1.5 -> 1.3828864 | H82: 11 | I82: =Liquor!$G82/Liquor!$H82 -> 0.12571695 | M82: =SUM(Liquor!$J82:$L82) -> 0 | N82: =$M82*$E82 -> 0
A83: 1 Liter | B83: 33.814 | C83: Jack Daniels Old No. 7 Whiskey | D83: whiskey | E83: 28.22 | F83: =$E83/$B83 -> 0.83456556 | G83: =Liquor!$F83*1.5 -> 1.2518483 | H83: 11 | I83: =Liquor!$G83/Liquor!$H83 -> 0.1138044 | J83: 0.75 | M83: =SUM(Liquor!$J83:$L83) -> 0.75 | N83: =$M83*$E83 -> 21.165
A84: 750ml | B84: 25.36 | C84: Jameson Irish | D84: whisky | E84: 28.58 | F84: =$E84/$B84 -> 1.1269716 | G84: =Liquor!$F84*1.5 -> 1.6904574 | H84: 12 | I84: =Liquor!$G84/Liquor!$H84 -> 0.14087145 | M84: =SUM(Liquor!$J84:$L84) -> 0 | N84: =$M84*$E84 -> 0
A85: 1 Liter | B85: 33.814 | C85: Jameson Irish | D85: whisky | E85: 38.34 | F85: =$E85/$B85 -> 1.1338499 | G85: =Liquor!$F85*1.5 -> 1.7007748 | H85: 11 | I85: =Liquor!$G85/Liquor!$H85 -> 0.15461589 | M85: =SUM(Liquor!$J85:$L85) -> 0 | N85: =$M85*$E85 -> 0
A86: 750ml | B86: 25.36 | C86: Jefferson's Bourbon | D86: bourbon | E86: 25.59 | F86: =$E86/$B86 -> 1.0090694 | G86: =Liquor!$F86*1.5 -> 1.5136041 | I86: =Liquor!$G86/Liquor!$H86 -> #DIV/0! | J86: 0.5 | M86: =SUM(Liquor!$J86:$L86) -> 0.5 | N86: =$M86*$E86 -> 12.795
A87: 1 Liter | B87: 33.814 | C87: Knob Creek Rye | D87: rye | E87: 39.08 | F87: =$E87/$B87 -> 1.1557343 | G87: =Liquor!$F87*1.5 -> 1.7336015 | H87: 15 | I87: =Liquor!$G87/Liquor!$H87 -> 0.11557343 | J87: 0.8 | M87: =SUM(Liquor!$J87:$L87) -> 0.8 | N87: =$M87*$E87 -> 31.264
A88: 750ml | B88: 25.36 | C88: Maker's Mark Bourbon | D88: bourbon | E88: 29.16 | F88: =$E88/$B88 -> 1.1498423 | G88: =Liquor!$F88*1.5 -> 1.7247634 | H88: 12 | I88: =Liquor!$G88/Liquor!$H88 -> 0.14373028 | M88: =SUM(Liquor!$J88:$L88) -> 0 | N88: =$M88*$E88 -> 0
A89: 1 Liter | B89: 33.814 | C89: Maker's Mark Bourbon | D89: bourbon | E89: 31.86 | F89: =$E89/$B89 -> 0.94221328 | G89: =Liquor!$F89*1.5 -> 1.4133199 | H89: 12 | I89: =Liquor!$G89/Liquor!$H89 -> 0.11777666 | J89: 0.5 | M89: =SUM(Liquor!$J89:$L89) -> 0.5 | N89: =$M89*$E89 -> 15.93
A90: 750ml | B90: 25.36 | C90: Milam & Greene Single Barrel | D90: bourbon | E90: 50.37 | F90: =$E90/$B90 -> 1.9861987 | G90: =Liquor!$F90*1.5 -> 2.9792981 | H90: 18 | I90: =Liquor!$G90/Liquor!$H90 -> 0.16551656 | J90: 0.3 | M90: =SUM(Liquor!$J90:$L90) -> 0.3 | N90: =$M90*$E90 -> 15.111
A91: 750ml | B91: 25.36 | C91: Mitcher's Rye | D91: rye | E91: 42.82 | F91: =$E91/$B91 -> 1.6884858 | G91: =Liquor!$F91*1.5 -> 2.5327287 | H91: 16 | I91: =Liquor!$G91/Liquor!$H91 -> 0.15829554 | J91: 0.4 | M91: =SUM(Liquor!$J91:$L91) -> 0.4 | N91: =$M91*$E91 -> 17.128
A92: 750ml | B92: 25.36 | C92: Nikka Coffey Grain | D92: whisky | E92: 58.59 | F92: =$E92/$B92 -> 2.3103312 | G92: =Liquor!$F92*1.5 -> 3.4654968 | H92: 18 | I92: =Liquor!$G92/Liquor!$H92 -> 0.1925276 | J92: 0.7 | M92: =SUM(Liquor!$J92:$L92) -> 0.7 | N92: =$M92*$E92 -> 41.013
A93: 700mL | B93: 23.6 | C93: Old Fitzgerald 7yr | D93: bourbon | E93: 47.43 | F93: =$E93/$B93 -> 2.0097458 | G93: =Liquor!$F93*1.5 -> 3.0146186 | H93: 23 | I93: =Liquor!$G93/Liquor!$H93 -> 0.13107038 | J93: 0.8 | M93: =SUM(Liquor!$J93:$L93) -> 0.8 | N93: =$M93*$E93 -> 37.944
A94: 750ml | B94: 25.36 | C94: Old Forrester King Ranch | D94: bourbon | E94: 86.2 | F94: =$E94/$B94 -> 3.3990536 | G94: =Liquor!$F94*1.5 -> 5.0985804 | H94: 26 | I94: =Liquor!$G94/Liquor!$H94 -> 0.19609925 | J94: 0.75 | M94: =SUM(Liquor!$J94:$L94) -> 0.75 | N94: =$M94*$E94 -> 64.65
A95: 1 Liter | B95: 33.814 | C95: Old Forrester Rye | D95: rye | E95: 25.32 | F95: =$E95/$B95 -> 0.74880227 | G95: =Liquor!$F95*1.5 -> 1.1232034 | H95: 12 | I95: =Liquor!$G95/Liquor!$H95 -> 0.093600284 | J95: 0.55 | M95: =SUM(Liquor!$J95:$L95) -> 0.55 | N95: =$M95*$E95 -> 13.926
A96: 1 Liter | B96: 33.814 | C96: Old Forester Classic 86 Proof | D96: bourbon | E96: 23.3 | F96: =$E96/$B96 -> 0.6890637 | G96: =Liquor!$F96*1.5 -> 1.0335956 | H96: 14 | I96: =Liquor!$G96/Liquor!$H96 -> 0.073828254 | J96: 0.7 | M96: =SUM(Liquor!$J96:$L96) -> 0.7 | N96: =$M96*$E96 -> 16.31
A97: 750ml | B97: 25.36 | C97: Orphan Barrel Fanged Pursuit | D97: bourbon | E97: 172.5 | F97: =$E97/$B97 -> 6.8020505 | G97: =Liquor!$F97*1.5 -> 10.203076 | H97: 38 | I97: =Liquor!$G97/Liquor!$H97 -> 0.26850199 | J97: 0.5 | M97: =SUM(Liquor!$J97:$L97) -> 0.5 | N97: =$M97*$E97 -> 86.25
A98: 1 Liter | B98: 33.814 | C98: Powers Gold Label Irish Whiskey | D98: whisky | E98: 37.91 | F98: =$E98/$B98 -> 1.1211333 | G98: =Liquor!$F98*1.5 -> 1.6816999 | H98: 12 | I98: =Liquor!$G98/Liquor!$H98 -> 0.14014166 | J98: 0.4 | M98: =SUM(Liquor!$J98:$L98) -> 0.4 | N98: =$M98*$E98 -> 15.164
A99: 750ml | B99: 25.36 | C99: Rittenhouse Rye | D99: rye | E99: 24.14 | F99: =$E99/$B99 -> 0.95189274 | G99: =Liquor!$F99*1.5 -> 1.4278391 | H99: 12 | I99: =Liquor!$G99/Liquor!$H99 -> 0.11898659 | J99: 1 | M99: =SUM(Liquor!$J99:$L99) -> 1 | N99: =$M99*$E99 -> 24.14
A100: 1 Liter | B100: 33.814 | C100: Rittenhouse Rye | D100: rye | E100: 29.33 | F100: =$E100/$B100 -> 0.8673922 | G100: =Liquor!$F100*1.5 -> 1.3010883 | H100: 12 | I100: =Liquor!$G100/Liquor!$H100 -> 0.10842403 | M100: =SUM(Liquor!$J100:$L100) -> 0 | N100: =$M100*$E100 -> 0
A101: 750ml | B101: 25.36 | C101: Redbreast 12Y | D101: whisky | E101: 67.79 | F101: =$E101/$B101 -> 2.6731073 | G101: =Liquor!$F101*1.5 -> 4.0096609 | H101: 17 | I101: =Liquor!$G101/Liquor!$H101 -> 0.2358624 | J101: 0.2 | M101: =SUM(Liquor!$J101:$L101) -> 0.2 | N101: =$M101*$E101 -> 13.558
...

Sheet Wine
A1: Wine
A2: Size | B2: Ounces | C2: Name | D2: W/R/S | E2: Cost | F2: Cost per OZ | G2: Menu Price Bottle | H2: Cost Bottle% | I2: Menu Price Glass 5oz | J2: Cost Glass% | K2: Main Bar | L2: Pool Bar | M2: Restaurant, Server Alley & Wine Cubby | N2: Wine Storage | O2: Total | P2: Total Value
A3: 750ml | B3: 25.36 | C3: MiraMe Cava | D3: BTG Sparkling | E3: 9.25 | F3: =E3/B3 -> 0.36474763 | G3: 40 | H3: =Wine!$E3/Wine!$G3 -> 0.23125 | I3: 10 | J3: =(Wine!$F3*5)/Wine!$I3 -> 0.18237382 | K3: 3 | M3: 19.6 | N3: 48 | O3: =SUM(K3:N3) -> 70.6 | P3: =Wine!$O3*Wine!$E3 -> 653.05
C4: Wycliffe | K4: 2
A5: 750ml | B5: 25.36 | C5: Fidora Prosecco NV | D5: BTG Sparkling | E5: 11.75 | F5: =E5/B5 -> 0.46332808 | G5: 48 | H5: =Wine!$E5/Wine!$G5 -> 0.24479167 | I5: 12 | J5: =(Wine!$F5*5)/Wine!$I5 -> 0.19305336 | K5: 2.7 | M5: 5 | O5: =SUM(K5:N5) -> 7.7 | P5: =Wine!$O5*Wine!$E5 -> 90.475
A6: 750ml | B6: 25.36 | C6: El Bajio Sparkling Brut | D6: BTG Sparkling | E6: 13.75 | F6: =E6/B6 -> 0.54219243 | G6: 58 | H6: =Wine!$E6/Wine!$G6 -> 0.23706897 | I6: 15 | J6: =(Wine!$F6*5)/Wine!$I6 -> 0.18073081 | M6: 5.5 | O6: =SUM(K6:N6) -> 5.5 | P6: =Wine!$O6*Wine!$E6 -> 75.625
A7: 750ml | B7: 25.36 | C7: Soto Vino Once Upon a Time in TX Rose | D7: BTG Rose | E7: 16.5 | F7: =E7/B7 -> 0.65063091 | G7: 62 | H7: =Wine!$E7/Wine!$G7 -> 0.26612903 | I7: 16 | J7: =(Wine!$F7*5)/Wine!$I7 -> 0.20332216 | O7: =SUM(K7:N7) -> 0 | P7: =Wine!$O7*Wine!$E7 -> 0
A8: 750ml | B8: 25.36 | C8: Ambratu Orange 2023 | D8: BTG Orange | E8: 16 | F8: =E8/B8 -> 0.63091483 | G8: 60 | H8: =Wine!$E8/Wine!$G8 -> 0.26666667 | I8: 16 | J8: =(Wine!$F8*5)/Wine!$I8 -> 0.19716088 | K8: 2 | M8: 16 | N8: 12 | O8: =SUM(K8:N8) -> 30 | P8: =Wine!$O8*Wine!$E8 -> 480
A9: 750ml | B9: 25.36 | C9: Frenzy Sauvignon Blanc 2023 (HH) | D9: BTG White | E9: 9.67 | F9: =E9/B9 -> 0.38130915 | G9: 48 | H9: =Wine!$E9/Wine!$G9 -> 0.20145833 | I9: 12 | J9: =(Wine!$F9*5)/Wine!$I9 -> 0.15887881 | K9: 1 | M9: 20 | O9: =SUM(K9:N9) -> 21 | P9: =Wine!$O9*Wine!$E9 -> 203.07
A10: 750ml | B10: 25.36 | C10: Stags' Leap Chardonnay 2023 | D10: BTG White | E10: 18 | F10: =E10/B10 -> 0.70977918 | G10: 72 | H10: =Wine!$E10/Wine!$G10 -> 0.25 | I10: 18 | J10: =(Wine!$F10*5)/Wine!$I10 -> 0.19716088 | K10: 0.8 | M10: 24.9 | N10: 12 | O10: =SUM(K10:N10) -> 37.7 | P10: =Wine!$O10*Wine!$E10 -> 678.6
A11: 750ml | B11: 25.36 | C11: Terlato Pinot Grigio 2022 | D11: BTG White | E11: 12 | F11: =E11/B11 -> 0.47318612 | G11: 52 | H11: =Wine!$E11/Wine!$G11 -> 0.23076923 | I11: 14 | J11: =(Wine!$F11*5)/Wine!$I11 -> 0.16899504 | K11: 1 | M11: 3 | O11: =SUM(K11:N11) -> 4 | P11: =Wine!$O11*Wine!$E11 -> 48
A12: 750ml | B12: 25.36 | C12: Herencia Altes Garnatxa Blanc 2022 | D12: BTG White | E12: 10 | F12: =E12/B12 -> 0.39432177 | G12: 48 | H12: =Wine!$E12/Wine!$G12 -> 0.20833333 | I12: 12 | J12: =(Wine!$F12*5)/Wine!$I12 -> 0.16430074 | K12: 2.2 | M12: 16 | O12: =SUM(K12:N12) -> 18.2 | P12: =Wine!$O12*Wine!$E12 -> 182
A13: 750ml | B13: 25.36 | C13: Presqu'ile Pinot Noir 2023 | D13: BTG White | E13: 16.75 | F13: =E13/B13 -> 0.66048896 | G13: 68 | H13: =Wine!$E13/Wine!$G13 -> 0.24632353 | I13: 17 | J13: =(Wine!$F13*5)/Wine!$I13 -> 0.19426146 | K13: 2.3 | M13: 10 | N13: 12 | O13: =SUM(K13:N13) -> 24.3 | P13: =Wine!$O13*Wine!$E13 -> 407.025
A14: 750ml | B14: 25.36 | C14: Casa Madero 3V 2021 (6pk) | D14: BTG Red | E14: 14.81 | F14: =E14/B14 -> 0.58399054 | G14: 59 | H14: =Wine!$E14/Wine!$G14 -> 0.25101695 | I14: 16 | J14: =(Wine!$F14*5)/Wine!$I14 -> 0.18249704 | K14: 1.2 | M14: 13 | O14: =SUM(K14:N14) -> 14.2 | P14: =Wine!$O14*Wine!$E14 -> 210.302
A15: 750ml | B15: 25.36 | C15: Soto Vino Slow Dancing | D15: BTG Red | E15: 16.5 | F15: =E15/B15 -> 0.65063091 | G15: 62 | H15: =Wine!$E15/Wine!$G15 -> 0.26612903 | I15: 16 | J15: =(Wine!$F15*5)/Wine!$I15 -> 0.20332216 | M15: 20 | O15: =SUM(K15:N15) -> 20 | P15: =Wine!$O15*Wine!$E15 -> 330
A16: 750ml | B16: 25.36 | C16: Ch Ste Michelle Cold Creek Vyd Cab Sauv 2020 (6pk) | D16: BTG Red | E16: 15 | F16: =E16/B16 -> 0.59148265 | G16: 60 | H16: =Wine!$E16/Wine!$G16 -> 0.25 | I16: 16 | J16: =(Wine!$F16*5)/Wine!$I16 -> 0.18483833 | K16: 0.8 | M16: 13 | N16: 6 | O16: =SUM(K16:N16) -> 19.8 | P16: =Wine!$O16*Wine!$E16 -> 297
A17: 750ml | B17: 25.36 | C17: Sterling Cabernet Sauvignon 2023 (HH) | D17: Happy Hour Wine | E17: 6 | F17: =E17/B17 -> 0.23659306 | G17: 44 | H17: =Wine!$E17/Wine!$G$17 -> 0.13636364 | I17: 11 | J17: =(Wine!$F17*5)/Wine!$I$17 -> 0.1075423 | K17: 4.6 | O17: =SUM(K17:N17) -> 4.6 | P17: =Wine!$O17*Wine!$E17 -> 27.6
A18: 375ml | B18: 12.68 | C18: Louis Roederer Brut Collection 246 (375mL) | D18: Sparkling | E18: 27 | F18: =E18/B18 -> 2.1293375 | G18: 75 | H18: =Wine!$E18/Wine!$G18 -> 0.36 | I18: 37.5 | J18: =(Wine!$F18*5)/Wine!$I18 -> 0.28391167 | M18: 3 | N18: 2 | O18: =SUM(K18:N18) -> 5 | P18: =Wine!$O18*Wine!$E18 -> 135
A19: 750ml | B19: 25.36 | C19: Antech Cuvee Francoise Cremant de Limoux NV | D19: Sparkling | E19: 13.5 | F19: =E19/B19 -> 0.53233438 | G19: 60 | H19: =Wine!$E19/Wine!$G19 -> 0.225 | I19: 16 | J19: =(Wine!$F19*5)/Wine!$I19 -> 0.1663545 | O19: =SUM(K19:N19) -> 0 | P19: =Wine!$O19*Wine!$E19 -> 0
A20: 750ml | B20: 25.36 | C20: Jean Veselle Brut | D20: Sparkling | E20: 39.75 | F20: =E20/B20 -> 1.567429 | G20: 155 | H20: =Wine!$E20/Wine!$G20 -> 0.25645161 | I20: 39.75 | J20: =(Wine!$F20*5)/Wine!$I20 -> 0.19716088 | M20: 9 | O20: =SUM(K20:N20) -> 9 | P20: =Wine!$O20*Wine!$E20 -> 357.75
A21: 750ml | B21: 25.36 | C21: Veuve Cliquot Yellow Label | D21: Sparkling | E21: 65.9 | F21: =E21/B21 -> 2.5985804 | G21: 170 | H21: =Wine!$E21/Wine!$G21 -> 0.38764706 | I21: 65.9 | J21: =(Wine!$F21*5)/Wine!$I21 -> 0.19716088 | M21: 1 | O21: =SUM(K21:N21) -> 1 | P21: =Wine!$O21*Wine!$E21 -> 65.9
A22: 750ml | B22: 25.36 | C22: GH Mumm Cordon Rosé | M22: 1
A23: 750ml | B23: 25.36 | C23: Ruinart Rosé | D23: Sparkling | E23: 80.99 | F23: =E23/B23 -> 3.193612 | G23: 240 | H23: =Wine!$E23/Wine!$G23 -> 0.33745833 | I23: 80.99 | J23: =(Wine!$F23*5)/Wine!$I23 -> 0.19716088 | M23: 1 | O23: =SUM(K23:N23) -> 1 | P23: =Wine!$O23*Wine!$E23 -> 80.99
A24: 750ml | B24: 25.36 | C24: Can Sumoi La Rosa Rose 2023 | D24: Rosé | E24: 13 | F24: =E24/B24 -> 0.5126183 | G24: 52 | H24: =Wine!$E24/Wine!$G24 -> 0.25 | I24: 13 | J24: =(Wine!$F24*5)/Wine!$I24 -> 0.19716088 | M24: 7 | O24: =SUM(K24:N24) -> 7 | P24: =Wine!$O24*Wine!$E24 -> 91
A25: 750ml | B25: 25.36 | C25: Soto Vino Desert Rose 2023 | D25: Rosé | E25: 18 | F25: =E25/B25 -> 0.70977918 | G25: 68 | H25: =Wine!$E25/Wine!$G25 -> 0.26470588 | I25: 17 | J25: =(Wine!$F25*5)/Wine!$I25 -> 0.20875858 | K25: 0.8 | M25: 10 | N25: 12 | O25: =SUM(K25:N25) -> 22.8 | P25: =Wine!$O25*Wine!$E25 -> 410.4
A26: 750ml | B26: 25.36 | C26: Soto Vino Orange Wine | E26: 18 | F26: =E26/B26 -> 0.70977918 | G26: 68 | H26: =Wine!$E26/Wine!$G26 -> 0.26470588 | I26: 17 | J26: =(Wine!$F26*5)/Wine!$I26 -> 0.20875858 | M26: 1 | N26: 20 | O26: =SUM(K26:N26) -> 21 | P26: =Wine!$O26*Wine!$E26 -> 378
A27: 750ml | B27: 25.36 | C27: Rombauer Sauvignon Blanc 2023 | D27: White | E27: 20.99 | F27: =E27/B27 -> 0.82768139 | G27: 65 | H27: =Wine!$E27/Wine!$G$27 -> 0.32292308 | I27: 16 | J27: =(Wine!$F27*5)/Wine!$I$27 -> 0.25865043 | M27: 2 | O27: =SUM(K27:N27) -> 2 | P27: =Wine!$O27*Wine!$E27 -> 41.98
A28: 750ml | B28: 25.36 | C28: Chalk Hill Sauvignon Blanc 2023 | D28: White | E28: 14 | F28: =E28/B28 -> 0.55205047 | G28: 60 | H28: =Wine!$E28/Wine!$G$27 -> 0.21538462 | I28: 16 | J28: =(Wine!$F28*5)/Wine!$I$27 -> 0.17251577 | O28: =SUM(K28:N28) -> 0 | P28: =Wine!$O28*Wine!$E28 -> 0
A29: 750ml | B29: 25.36 | C29: La Chiara Gavi 2020 | D29: White | E29: 16 | F29: =E29/B29 -> 0.63091483 | G29: 64 | H29: =Wine!$E29/Wine!$G29 -> 0.25 | I29: 16 | J29: =(Wine!$F29*5)/Wine!$I29 -> 0.19716088 | O29: =SUM(K29:N29) -> 0 | P29: =Wine!$O29*Wine!$E29 -> 0
A30: 750ml | B30: 25.36 | C30: Vietti Roero Arneis 2023 | D30: White | E30: 16.09 | F30: =E30/B30 -> 0.63446372 | G30: 62 | H30: =Wine!$E30/Wine!$G$30 -> 0.25951613 | I30: 16 | J30: =(Wine!$F30*5)/Wine!$I$30 -> 0.19826991 | M30: 3 | N30: 2 | O30: =SUM(K30:N30) -> 5 | P30: =Wine!$O30*Wine!$E30 -> 80.45
A31: 750ml | B31: 25.36 | C31: Seppeltsfield Riesling | D31: White | E31: 15.75 | F31: =E31/B31 -> 0.62105678 | G31: 60 | H31: =Wine!$E31/Wine!$G$30 -> 0.25403226 | I31: 16 | J31: =(Wine!$F31*5)/Wine!$I$30 -> 0.19408024 | M31: 7 | O31: =SUM(K31:N31) -> 7 | P31: =Wine!$O31*Wine!$E31 -> 110.25
A32: 750ml | B32: 25.36 | C32: Chalone Chardonnay 2022 | D32: White | E32: 15 | F32: =E32/B32 -> 0.59148265 | G32: 60 | H32: =Wine!$E32/Wine!$G$30 -> 0.24193548 | I32: 16 | J32: =(Wine!$F32*5)/Wine!$I$30 -> 0.18483833 | M32: 3 | N32: 10 | O32: =SUM(K32:N32) -> 13 | P32: =Wine!$O32*Wine!$E32 -> 195
A33: 750ml | B33: 25.36 | C33: G. Vrignaud Petit Chablis 2022 | D33: White | E33: 22.12 | F33: =E33/B33 -> 0.87223975 | G33: 86 | H33: =Wine!$E33/Wine!$G33 -> 0.2572093 | I33: 23 | J33: =(Wine!$F33*5)/Wine!$I33 -> 0.18961734 | M33: 4 | O33: =SUM(K33:N33) -> 4 | P33: =Wine!$O33*Wine!$E33 -> 88.48
A34: 750ml | B34: 25.36 | C34: Olivier LeFlaive Bourgogne "Les Setilles" 2020 | D34: White | E34: 28 | F34: =E34/B34 -> 1.1041009 | G34: 95 | H34: =Wine!$E34/Wine!$G34 -> 0.29473684 | I34: 24 | J34: =(Wine!$F34*5)/Wine!$I34 -> 0.23002103 | M34: 4 | O34: =SUM(K34:N34) -> 4 | P34: =Wine!$O34*Wine!$E34 -> 112
A35: 750ml | B35: 25.36 | C35: Louis Latour Meursault 2019 | D35: White | E35: 37.38 | F35: =E35/B35 -> 1.4739748 | G35: 220 | H35: =Wine!$E35/Wine!$G35 -> 0.16990909 | I35: 50 | J35: =(Wine!$F35*5)/Wine!$I35 -> 0.14739748 | M35: 2 | O35: =SUM(K35:N35) -> 2 | P35: =Wine!$O35*Wine!$E35 -> 74.76
A36: 750ml | B36: 25.36 | C36: Pedernales Albarino 2021 (TX) | D36: White | E36: 14 | F36: =E36/B36 -> 0.55205047 | G36: 56 | H36: =Wine!$E36/Wine!$G36 -> 0.25 | I36: 14 | J36: =(Wine!$F36*5)/Wine!$I36 -> 0.19716088 | O36: =SUM(K36:N36) -> 0 | P36: =Wine!$O36*Wine!$E36 -> 0
A37: 750ml | B37: 25.36 | C37: Soto Vino 24 Sauvage 2024 | D37: Red | E37: 20 | F37: =E37/B37 -> 0.78864353 | G37: 80 | H37: =Wine!$E37/Wine!$G37 -> 0.25 | I37: 20 | J37: =(Wine!$F37*5)/Wine!$I37 -> 0.19716088 | M37: 13 | O37: =SUM(K37:N37) -> 13 | P37: =Wine!$O37*Wine!$E37 -> 260
A38: 750ml | B38: 25.36 | C38: Teutonic Crow Valley Vyd Pinot Noir 2023 | D38: Red | E38: 26 | F38: =E38/B38 -> 1.0252366 | G38: 90 | H38: =Wine!$E38/Wine!$G38 -> 0.28888889 | I38: 23 | J38: =(Wine!$F38*5)/Wine!$I38 -> 0.22287752 | M38: 3.7 | O38: =SUM(K38:N38) -> 3.7 | P38: =Wine!$O38*Wine!$E38 -> 96.2
A39: 750ml | B39: 25.36 | C39: Moshin Vineyards Pinot Noir 2020 | D39: Red | E39: 26 | F39: =E39/B39 -> 1.0252366 | G39: 75 | H39: =Wine!$E39/Wine!$G39 -> 0.34666667 | I39: 20 | J39: =(Wine!$F39*5)/Wine!$I39 -> 0.25630915 | M39: 2 | N39: 12 | O39: =SUM(K39:N39) -> 14 | P39: =Wine!$O39*Wine!$E39 -> 364
A40: 750ml | B40: 25.36 | C40: Montenidoli Toscana Rosso 2020 | D40: Red | E40: 18.2 | F40: =E40/B40 -> 0.71766562 | G40: 70 | H40: =Wine!$E40/Wine!$G40 -> 0.26 | I40: 18 | J40: =(Wine!$F40*5)/Wine!$I40 -> 0.19935156 | K40: 1.4 | O40: =SUM(K40:N40) -> 1.4 | P40: =Wine!$O40*Wine!$E40 -> 25.48
A41: 750ml | B41: 25.36 | C41: Montenidoli Toscana Rosso 2017 | D41: Red | E41: 59 | F41: =E41/B41 -> 2.3264984 | H41: =Wine!$E41/Wine!$G41 -> #DIV/0! | I41: 18 | J41: =(Wine!$F41*5)/Wine!$I41 -> 0.64624956 | N41: 23 | O41: =SUM(K41:N41) -> 23 | P41: =Wine!$O41*Wine!$E41 -> 1357
A42: 750ml | B42: 25.36 | C42: Mario Bagella 1Sorso Cannonau 2022 | D42: Red | E42: 14 | F42: =E42/B42 -> 0.55205047 | G42: 58 | H42: =Wine!$E42/Wine!$G42 -> 0.24137931 | I42: 14 | J42: =(Wine!$F42*5)/Wine!$I42 -> 0.19716088 | M42: 9 | O42: =SUM(K42:N42) -> 9 | P42: =Wine!$O42*Wine!$E42 -> 126
A43: 750ml | B43: 25.36 | C43: Olivier Cazenave Bel Rouge NV | D43: Red | E43: 14 | F43: =E43/B43 -> 0.55205047 | G43: 58 | H43: =Wine!$E43/Wine!$G43 -> 0.24137931 | I43: 14 | J43: =(Wine!$F43*5)/Wine!$I43 -> 0.19716088 | K43: 4 | M43: 14 | O43: =SUM(K43:N43) -> 18 | P43: =Wine!$O43*Wine!$E43 -> 252
A44: 750ml | B44: 25.36 | C44: Seppeltsfield Shiraz 2022 | D44: Red | E44: 15.75 | F44: =E44/B44 -> 0.62105678 | G44: 70 | H44: =Wine!$E44/Wine!$G44 -> 0.225 | I44: 18 | J44: =(Wine!$F44*5)/Wine!$I44 -> 0.17251577 | M44: 7 | O44: =SUM(K44:N44) -> 7 | P44: =Wine!$O44*Wine!$E44 -> 110.25
A45: 750ml | B45: 25.36 | C45: Tococo de Alcohuaz Syrah 2019 (Chile) | D45: Red | E45: 48 | F45: =E45/B45 -> 1.8927445 | G45: 185 | H45: =Wine!$E45/Wine!$G45 -> 0.25945946 | I45: 48 | J45: =(Wine!$F45*5)/Wine!$I45 -> 0.19716088 | O45: =SUM(K45:N45) -> 0 | P45: =Wine!$O45*Wine!$E45 -> 0
A46: 750ml | B46: 25.36 | C46: Aalto Ribera del Duero 2021 | D46: Red | E46: 46 | F46: =E46/B46 -> 1.8138801 | G46: 150 | H46: =Wine!$E46/Wine!$G46 -> 0.30666667 | I46: 43 | J46: =(Wine!$F46*5)/Wine!$I46 -> 0.21091629 | M46: 1 | O46: =SUM(K46:N46) -> 1 | P46: =Wine!$O46*Wine!$E46 -> 46
A47: 750ml | B47: 25.36 | C47: Turley Juvenile Zin 2022/2023 | D47: Red | E47: 20.5 | F47: =E47/B47 -> 0.80835962 | G47: 80 | H47: =Wine!$E47/Wine!$G47 -> 0.25625 | I47: 20 | J47: =(Wine!$F47*5)/Wine!$I47 -> 0.20208991 | M47: 13 | O47: =SUM(K47:N47) -> 13 | P47: =Wine!$O47*Wine!$E47 -> 266.5
A48: 750ml | B48: 25.36 | C48: Domaine Gayrard Duras 2022 | D48: Red | E48: 15.2 | F48: =E48/B48 -> 0.59936909 | G48: 60 | H48: =Wine!$E48/Wine!$G48 -> 0.25333333 | I48: 16 | J48: =(Wine!$F48*5)/Wine!$I48 -> 0.18730284 | N48: 1 | O48: =SUM(K48:N48) -> 1 | P48: =Wine!$O48*Wine!$E48 -> 15.2
A49: 500mL | B49: 16.91 | C49: Clarendelle Amberwine 2015 | D49: Dessert Wine | E49: 25.75 | F49: =E49/B49 -> 1.5227676 | G49: 90 | H49: =Wine!$E49/Wine!$G49 -> 0.28611111 | I49: 17 | J49: =(Wine!$F49*3)/Wine!$I49 -> 0.26872369 | M49: 3.5 | O49: =SUM(K49:N49) -> 3.5 | P49: =Wine!$O49*Wine!$E49 -> 90.125
A50: 750ml | B50: 25.36 | C50: Taylor Fladgate Tawny Port 20yr | D50: Dessert Wine | E50: 46.75 | F50: =E50/B50 -> 1.8434543 | H50: =Wine!$E50/Wine!$G50 -> #DIV/0! | I50: 18 | J50: =(Wine!$F50*3)/Wine!$I50 -> 0.30724238 | K50: 0.6 | O50: =SUM(K50:N50) -> 0.6 | P50: =Wine!$O50*Wine!$E50 -> 28.05
C51: TOTAL | H51: =SUBTOTAL(101,Wine!$H$3:$H$48) -> #DIV/0! | J51: =SUBTOTAL(101,Wine!$J$3:$J$48) -> 0.20524621 | P51: =SUM(P3:P48) -> 8823.337
I53: =AVERAGE(H3:H48,J3:J48) -> #DIV/0!

Sheet Owners Collection
A1: Owner's Reserve Wine
A2: Size | B2: Ounces | C2: Name | D2: W/R/S | E2: Cost | F2: Cost per OZ | G2: Menu Price Bottle | H2: Cost Bottle% | I2: Menu Price Glass 5oz | J2: Cost Glass% | K2: Restaurant | L2: Office Wine Storage | M2: Total | N2: Total Value
A3: 750ml | B3: 25.36 | C3: Chateau Climens Grand Vin de Sauternes 2011 | D3: White | E3: 98.99 | F3: =E3/B3 -> 3.9033912 | G3: 175 | H3: ='Owners Collection'!$E3/'Owners Collection'!$G3 -> 0.56565714 | I3: 98.99 | J3: =('Owners Collection'!$F3*5)/'Owners Collection'!$I3 -> 0.19716088 | M3: =SUM(K3:L3) -> 0 | N3: ='Owners Collection'!$M3*'Owners Collection'!$E3 -> 0
A4: 750ml | B4: 25.36 | C4: Dom Robert Denogent Pouilly Fuisse Clos Reyssie 2016 | D4: White | E4: 42.63 | F4: =E4/B4 -> 1.6809937 | G4: 140 | H4: ='Owners Collection'!$E4/'Owners Collection'!$G4 -> 0.3045 | I4: 42.63 | J4: =('Owners Collection'!$F4*5)/'Owners Collection'!$I4 -> 0.19716088 | M4: =SUM(K4:L4) -> 0 | N4: ='Owners Collection'!$M4*'Owners Collection'!$E4 -> 0
A5: 750ml | B5: 25.36 | C5: Chalk Hill Estate Red 2013 | D5: Red | E5: 65 | F5: =E5/B5 -> 2.5630915 | G5: 165 | H5: ='Owners Collection'!$E5/'Owners Collection'!$G5 -> 0.39393939 | I5: 65 | J5: =('Owners Collection'!$F5*5)/'Owners Collection'!$I5 -> 0.19716088 | M5: =SUM(K5:L5) -> 0 | N5: ='Owners Collection'!$M5*'Owners Collection'!$E5 -> 0
A6: 750ml | B6: 25.36 | C6: Orin Swift Mercury Head Cav Sauv 2022 | D6: Red | E6: 120 | F6: =E6/B6 -> 4.7318612 | G6: 290 | H6: ='Owners Collection'!$E6/'Owners Collection'!$G6 -> 0.4137931 | I6: 135.2 | J6: =('Owners Collection'!$F6*5)/'Owners Collection'!$I6 -> 0.17499487 | M6: =SUM(K6:L6) -> 0 | N6: ='Owners Collection'!$M6*'Owners Collection'!$E6 -> 0
A7: 750ml | B7: 25.36 | C7: Spottswoode Cabernet Sauvignon 2021 | D7: Red | E7: 198 | F7: =E7/B7 -> 7.807571 | G7: 390 | H7: ='Owners Collection'!$E7/'Owners Collection'!$G7 -> 0.50769231 | I7: 185 | J7: =('Owners Collection'!$F7*5)/'Owners Collection'!$I7 -> 0.21101543 | M7: =SUM(K7:L7) -> 0 | N7: ='Owners Collection'!$M7*'Owners Collection'!$E7 -> 0
A8: 1L | B8: 33.814 | C8: Caymus Cabernet Sauvignon 2016 | D8: Red | E8: 237.66 | F8: =E8/B8 -> 7.0284498 | G8: 450 | H8: ='Owners Collection'!$E8/'Owners Collection'!$G8 -> 0.52813333 | I8: 237.66 | J8: =('Owners Collection'!$F8*5)/'Owners Collection'!$I8 -> 0.14786775 | M8: =SUM(K8:L8) -> 0 | N8: ='Owners Collection'!$M8*'Owners Collection'!$E8 -> 0
H9: =SUBTOTAL(101,'Owners Collection'!$H$3:$H$8) -> 0.45228588 | J9: =SUBTOTAL(101,'Owners Collection'!$J$3:$J$8) -> 0.18756012 | N9: =SUM('Owners Collection'!$N$3:$N$8) -> 0

Sheet Beer
A1: Beer
B2: Size. | C2: Ounces | D2: Name | E2: Cost | F2: Cost/ OZ | G2: Menu $ | H2: Cost% | I2: Main Bar | J2: Pool Bar | K2: Cooler | L2: Total | M2: Total Value
B3: 1/4bbl | C3: 992 | D3: 512 Kolsch | E3: 110 | F3: =$E3/$C3 -> 0.1108871 | G3: 8 | H3: =(Beer!$F3*15)/Beer!$G3 -> 0.20791331 | K3: 1 | L3: =SUM(I3:K3) -> 1 | M3: =$L3*$E3 -> 110
B4: 1/6bbl | C4: 640 | D4: Fast Friends Marzen Lager | E4: 80 | F4: =$E4/$C4 -> 0.125 | G4: 8.5 | H4: =(Beer!$F4*15)/Beer!$G4 -> 0.22058824 | K4: 1 | L4: =SUM(I4:K4) -> 1 | M4: =$L4*$E4 -> 80
B5: 1/6bbl | C5: 640 | D5: Save the World Cerveza | E5: 80 | F5: =$E5/$C5 -> 0.125 | G5: 8 | H5: =(Beer!$F5*15)/Beer!$G5 -> 0.234375 | K5: 2 | L5: =SUM(I5:K5) -> 2 | M5: =$L5*$E5 -> 160
B6: 1/6bbl | C6: 640 | D6: Save the World Chasing Broncos IPA | E6: 90 | F6: =$E6/$C6 -> 0.140625 | G6: 10 | H6: =(Beer!$F6*15)/Beer!$G6 -> 0.2109375 | K6: 1 | L6: =SUM(I6:K6) -> 1 | M6: =$L6*$E6 -> 90
B7: Can | C7: 12 | D7: Lone Star | E7: 0.88 | F7: =$E7/$C7 -> 0.073333333 | G7: 6 | H7: =(Beer!$F7*15)/Beer!$G7 -> 0.18333333 | L7: =SUM(I7:K7) -> 0 | M7: =$L7*$E7 -> 0
B8: Can | C8: 12 | D8: Michelob Ultra | E8: 1.15 | F8: =$E8/$C8 -> 0.095833333 | G8: 7 | H8: =(Beer!$F8*15)/Beer!$G8 -> 0.20535714 | L8: =SUM(I8:K8) -> 0 | M8: =$L8*$E8 -> 0
B9: Can | C9: 12 | D9: Modelo Especial | E9: 1.19 | F9: =$E9/$C9 -> 0.099166667 | G9: 7 | H9: =(Beer!$F9*15)/Beer!$G9 -> 0.2125 | L9: =SUM(I9:K9) -> 0 | M9: =$L9*$E9 -> 0
B10: Can | C10: 12 | D10: Pacifico | E10: 1.36 | F10: =$E10/$C10 -> 0.11333333 | G10: 7 | H10: =(Beer!$F10*15)/Beer!$G10 -> 0.24285714 | L10: =SUM(I10:K10) -> 0 | M10: =$L10*$E10 -> 0
B11: Can | C11: 12 | D11: Miller Lite | E11: 1.03 | F11: =$E11/$C11 -> 0.085833333 | G11: 7 | H11: =(Beer!$F11*15)/Beer!$G11 -> 0.18392857 | L11: =SUM(I11:K11) -> 0 | M11: =$L11*$E11 -> 0
B12: Can | C12: 12 | D12: Coors Light | E12: 1.04 | F12: =$E12/$C12 -> 0.086666667 | G12: 6 | H12: =(Beer!$F12*15)/Beer!$G12 -> 0.21666667 | L12: =SUM(I12:K12) -> 0 | M12: =$L12*$E12 -> 0
B13: Can | C13: 12 | D13: 512 Juicy IPA | E13: 1.6 | F13: =$E13/$C13 -> 0.13333333 | G13: 8 | H13: =(Beer!$F13*15)/Beer!$G13 -> 0.25 | L13: =SUM(I13:K13) -> 0 | M13: =$L13*$E13 -> 0
B14: Can | C14: 12 | D14: Shiner Bock | E14: 1.13 | F14: =$E14/$C14 -> 0.094166667 | G14: 6 | H14: =(Beer!$F14*15)/Beer!$G14 -> 0.23541667 | L14: =SUM(I14:K14) -> 0 | M14: =$L14*$E14 -> 0
B15: Can | C15: 12 | D15: Austin Eastsider Dry | E15: 1.38 | F15: =$E15/$C15 -> 0.115 | G15: 6 | H15: =(Beer!$F15*15)/Beer!$G15 -> 0.2875 | L15: =SUM(I15:K15) -> 0 | M15: =$L15*$E15 -> 0
B16: Can | C16: 12 | D16: Austin Eastciders Blood Orange | E16: 1.38 | F16: =$E16/$C16 -> 0.115 | G16: 6 | H16: =(Beer!$F16*15)/Beer!$G16 -> 0.2875 | L16: =SUM(I16:K16) -> 0 | M16: =$L16*$E15 -> 0
B17: Can | C17: 12 | D17: Save the World Chasing Broncos IPA | E17: 2.6 | F17: =$E17/$C17 -> 0.21666667 | G17: 10 | H17: =(Beer!$F17*15)/Beer!$G17 -> 0.325 | L17: =SUM(I17:K17) -> 0 | M17: =$L17*$E17 -> 0
B18: Can | C18: 16 | D18: Fast Friends Matamata | E18: 3.75 | F18: =$E18/$C18 -> 0.234375 | G18: 8.5 | H18: =(Beer!$F18*15)/Beer!$G18 -> 0.41360294 | L18: =SUM(I18:K18) -> 0 | M18: =$L18*$E18 -> 0
B19: Can | C19: 16 | D19: Fast Friends Chibi Boots Pale Ale | E19: 3.75 | F19: =$E19/$C19 -> 0.234375 | G19: 8.5 | H19: =(Beer!$F19*15)/Beer!$G19 -> 0.41360294 | L19: =SUM(I19:K19) -> 0 | M19: =$L19*$E19 -> 0
B20: Can | C20: 16 | D20: Fast Friends Birthday Buds Dbl IPA | E20: 4.58 | F20: =$E20/$C20 -> 0.28625 | G20: 10 | H20: =(Beer!$F20*15)/Beer!$G20 -> 0.429375 | L20: =SUM(I20:K20) -> 0 | M20: =$L20*$E20 -> 0
B21: Can | C21: 12 | D21: 196 Suntory Seltzers | E21: 1.91 | F21: =$E21/$C21 -> 0.15916667 | G21: 10 | H21: =(Beer!$F21*15)/Beer!$G21 -> 0.23875 | L21: =SUM(I21:K21) -> 0 | M21: =$L21*$E21 -> 0
B22: Bottle | C22: 12 | D22: Heineken 0.0 | E22: 1.5 | F22: =$E22/$C22 -> 0.125 | G22: 7 | H22: =(Beer!$F22*15)/Beer!$G22 -> 0.26785714 | L22: =SUM(I22:K22) -> 0 | M22: =$L22*$E22 -> 0
B23: Bottle | C23: 12 | D23: Lone Star | E23: 0.93 | F23: =$E23/$C23 -> 0.0775 | G23: 6 | H23: =(Beer!$F23*15)/Beer!$G23 -> 0.19375 | L23: =SUM(I23:K23) -> 0 | M23: =$L23*$E23 -> 0
B24: Bottle | C24: 12 | D24: Michelob Ultra | E24: 1.44 | F24: =$E24/$C24 -> 0.12 | G24: 7 | H24: =(Beer!$F24*15)/Beer!$G24 -> 0.25714286 | L24: =SUM(I24:K24) -> 0 | M24: =$L24*$E24 -> 0
B25: Bottle | C25: 12 | D25: Miller Lite | E25: 1.04 | F25: =$E25/$C25 -> 0.086666667 | G25: 7 | H25: =(Beer!$F25*15)/Beer!$G25 -> 0.18571429 | L25: =SUM(I25:K25) -> 0 | M25: =$L25*$E25 -> 0
B26: Bottle | C26: 12 | D26: Shiner Bock | E26: 1.26 | F26: =$E26/$C26 -> 0.105 | G26: 7 | H26: =(Beer!$F26*15)/Beer!$G26 -> 0.225 | L26: =SUM(I26:K26) -> 0 | M26: =$L26*$E26 -> 0
B27: Bottle | C27: 12 | D27: Pacifico | E27: 1.37 | F27: =$E27/$C27 -> 0.11416667 | G27: 7 | H27: =(Beer!$F27*15)/Beer!$G27 -> 0.24464286 | L27: =SUM(I27:K27) -> 0 | M27: =$L27*$E27 -> 0
B28: Bottle | C28: 12 | D28: Modelo Especial | E28: 1.55 | F28: =$E28/$C28 -> 0.12916667 | G28: 7 | H28: =(Beer!$F28*15)/Beer!$G28 -> 0.27678571 | L28: =SUM(I28:K28) -> 0 | M28: =$L28*$E28 -> 0
B29: Bottle | C29: 12 | D29: Keg Deposit $50 | E29: 50 | K29: 15 | L29: =SUM(I29:K29) -> 15 | M29: =$L29*$E29 -> 750
B30: Bottle | C30: 12 | D30: Keg Deposit $30 (512 Brewing) | E30: 30 | K30: 1 | L30: =SUM(I30:K30) -> 1 | M30: =$L30*$E30 -> 30
H32: =SUBTOTAL(101,Beer!$H$4:$H$30) -> 0.25768736 | M32: =SUM(M3:M31) -> 1220

Sheet Produce
A1: PRODUCE
A2: NAME | B2: UOM | C2: Cost | D2: Cost per OZ | E2: Main Bar | F2: Pool Bar | G2: Restaurant | H2: Storage | I2: Total | J2: Total Value
A3: Olives | B3: case | J3: =I3*C3 -> 0
A4: Strawberries | B4: flat | J4: =I4*C4 -> 0
A5: Flowers | B5: boxes | J5: =I5*C5 -> 0
A6: limes | B6: case | J6: =I6*C6 -> 0
A7: lemons | B7: case | J7: =I7*C7 -> 0
A8: mint | B8: pound | J8: =I8*C8 -> 0
A9: Grenadine | J9: =I9*C9 -> 0
A10: Agave Sweet | J10: =I10*C10 -> 0
A11: Pineapple Juice | J11: =I11*C11 -> 0
A12: Cranberry Juice | J12: =I12*C12 -> 0
A13: basil | B13: pound | J13: =I13*C13 -> 0
A14: DRIED PEACHES | B14: LB | J14: =I14*C14 -> 0
A15: jalepeno | B15: pound | J15: =I15*C15 -> 0
A16: Watermelon | B16: pound | J16: =I16*C16 -> 0
A17: PUREE GREEN APPLE | B17: EA | J17: =I17*C17 -> 0
A18: PUREE YUZU | B18: EA | J18: =I18*C18 -> 0
A19: PUREE LADY LYCHEE | B19: EA | J19: =I19*C19 -> 0
A20: PUREE PINEAPPLE | B20: EA | J20: =I20*C20 -> 0
A21: PUREE PAPAYA | B21: EA | J21: =I21*C21 -> 0
A22: LEMON JUICE | B22: EA | J22: =I22*C22 -> 0
A23: GRAPEFRUIT JUICE | B23: EA | J23: =I23*C23 -> 0

Sheet Wine Waste
B3: VERBENA - (NOVEMBER:2025) WINE WASTE LOG
B5: Date: | C5: Wine | D5: Unit Lost | E5: Whole Sale Cost | F5: Total Loss
F7: =E7*D7 -> 0
F8: =E8*D8 -> 0
F9: =E9*D9 -> 0
F10: =E10*D10 -> 0
F11: =E11*D11 -> 0
F12: =E12*D12 -> 0
F13: =E13*D13 -> 0
F14: =E14*D14 -> 0
F15: =E15*D15 -> 0
F16: =E16*D16 -> 0
F17: =E17*D17 -> 0
F18: =E18*D18 -> 0
... F70: =E70*D70 -> 0
F71: Total: | G71: =SUM(F7:F70) -> 0

Sheet Cost
C1: Liquor | M1: Beer
C2: Liquor Cost Worksheet | M2: Beer Cost Worksheet
C3: Month/Year: | G3: 45986 | M3: Month/Year: | Q3: 45986
C4: Gross Beverage Revenue: | M4: Gross Beverage Revenue:
U5: WINESDAY 1/2 off PROMO
C6: Beginning Inventory | I6: 22196.24 | M6: Beginning Inventory | S6: 3079.62 | U6: Wine | V6: Sold | W6: Cost | X6: Total
X7: =(V7*W7)/2 -> 0
C8: Purchases | M8: Purchases | X8: =(V8*W8)/2 -> 0
C9: Petty Cash Purchases | K9: September Lobby Tastings - Liquor | M9: Petty Cash Purchases | X9: =(V9*W9)/2 -> 0
C10: Other Purchases | G10: specs | H10: 0 | J10: 17/L | K10: Margarita | L10: 68 | M10: Other Purchases | Q10: specs | R10: 0 | X10: =(V10*W10)/2 -> 0
C11: Total Purchases | I11: =SUM(H8:H10) -> 0 | J11: 17/L | K11: Old Fashioned | L11: 85 | M11: Total Purchases | S11: =SUM(R8:R10) -> 0 | X11: =(V11*W11)/2 -> 0
J12: 29/L | K12: Negroni | L12: 116 | X12: =(V12*W12)/2 -> 0
J13: 11/L | K13: Daiquiri | L13: 55 | X13: =(V13*W13)/2 -> 0
C14: Credit | E14: Retail Wall Reclass | K14: Total | L14: =SUM((L10:L13)) -> 324 | M14: Credit | N14: 192000 | O14: Retail Wall Reclass | X14: =(V14*W14)/2 -> 0
C15: Credit | D15: 53150 | E15: Evening Tasting | H15: =L14 -> 324 | M15: Credit | O15: Front Desk | X15: =(V15*W15)/2 -> 0
C16: Credit | D16: 15% cost | E16: HH Benefit | H16: =Z41 -> 0 | M16: Credit | N16: 15% cost | O16: HH Benefit | R16: =Z57 -> 0 | X16: =(V16*W16)/2 -> 0
C17: Credit | E17: Other - $2 off Promo | H17: 0 | M17: Credit | O17: Front Office Amenity | R17: =SUM(L34:L37) -> 0 | X17: =(V17*W17)/2 -> 0
C18: Credit | D18: Resort Pass | E18: Cabana Bottles (750mL) | H18: 37.98 | M18: Credit | O18: Other | R18: 0 | X18: =(V18*W18)/2 -> 0
X19: =(V19*W19)/2 -> 0
C20: Total Credits | I20: =SUM(H14:H18) -> 361.98 | M20: Total Credits | S20: =SUM(R14:R18) -> 0 | X20: =(V20*W20)/2 -> 0
X21: =(V21*W21)/2 -> 0
C22: Ending Inventory | I22: =Liquor!$N$400 -> 6528.7571 | M22: Ending Inventory | S22: =Beer!$M$32 -> 1220 | U22: TOTAL | W22: =SUM(W7:W21) -> 0 | X22: =(V22*W22)/2 -> 0
U23: Total | X23: =SUM(X7:X22) -> 0
C24: Cost of Bev Consumed | I24: =I6+I11-I20-I22 -> 15305.503 | M24: Cost of Bev Consumed | S24: =S6+S11-S20-S22 -> 1859.62
U25: Credit 50% | V25: =((X23+AC23)*0.5) -> 0
C26: Beverage Cost % | I26: =I24/G4 -> #DIV/0! | M26: Beverage Cost % | S26: =S24/Q4 -> #DIV/0!
C31: Wine | M31: TOTAL | U31: HH Cocktails | V31: Original Price | W31: HH Price | X31: Difference | Y31: Sold | Z31: Total
C32: Wine Cost Worksheet | K32: Front Office Amenity | M32: Total LBW Cost Worksheet | U32: UT margarita $5 | V32: 14 | W32: 5 | X32: =V32-W32 -> 9 | Z32: =X32*Y32 -> 0
C33: Month/Year: | G33: 45986 | J33: Beer | K33: Item | L33: Total | M33: Month/Year: | Q33: 45986 | U33: peach spritz | V33: 14 | W33: 10 | X33: =V33-W33 -> 4 | Z33: =X33*Y33 -> 0
C34: Gross Beverage Revenue: | M34: Gross Beverage Revenue: | Q34: =SUM(G4+G34+Q4+L76) -> 0 | U34: ranch water | V34: 15 | W34: 11 | X34: =V34-W34 -> 4 | Z34: =X34*Y34 -> 0
U35: $5 margaritas (Tuesdays) | V35: 14 | W35: 5 | X35: =V35-W35 -> 9 | Z35: =X35*Y35 -> 0
C36: Beginning Inventory | I36: 9363.76 | M36: Beginning Inventory | S36: =I6+I36+S6+N78 -> 34639.62 | U36: watermelon margarita | V36: 14 | W36: 10 | X36: =V36-W36 -> 4 | Z36: =X36*Y36 -> 0
U37: old fashioned | V37: 14 | W37: 10 | X37: =V37-W37 -> 4 | Z37: =X37*Y37 -> 0
C38: Purchases | J38: Wine | M38: Purchases | U38: shot casa lujo blanco | V38: 12 | W38: 4 | X38: =V38-W38 -> 8 | Z38: =X38*Y38 -> 0
C39: Petty Cash Purchases | M39: Petty Cash Purchases | U39: shot four roses bourbon | V39: 12 | W39: 4 | X39: =V39-W39 -> 8 | Z39: =X39*Y39 -> 0
C40: Other Purchases | G40: specs | H40: 0 | M40: Other Purchases | Q40: specs | R40: 0 | X40: total | Z40: =SUM(Z32:Z39) -> 0
C41: Total Purchases | I41: =SUM(H38:H40) -> 0 | M41: Total Purchases | S41: =SUM(R38:R40) -> 0 | X41: credit 18% | Z41: =Z40*0.18 -> 0
U43: HH Wine | V43: Original Price | W43: HH Price | X43: Difference | Y43: Sold | Z43: Total
D44: Debit GL Code | E44: Item | H44: Amount | K44: Sales Amenity | N44: Debit GL Code | O44: Item | R44: Amount | U44: bubbles | V44: 12 | W44: 8 | X44: =V44-W44 -> 4 | Z44: =X44*Y44 -> 0
C45: Credit | E45: Comp Breakfast | H45: 0 | J45: Date | K45: Item | L45: Total | M45: Credit | O45: Comp Breakfast | R45: 0 | U45: rose | V45: 16 | W45: 8 | X45: =V45-W45 -> 8 | Z45: =X45*Y45 -> 0
C46: Credit | E46: Lobby Food/Snacks | H46: 0 | K46: Veuve Cliquot - Hilton Exec | L46: 170 | M46: Credit | O46: Lobby Food/Snacks | R46: 0 | U46: white | V46: 12 | W46: 8 | X46: =V46-W46 -> 4 | Z46: =X46*Y46 -> 0
C47: Credit | E47: Manager Reception Food | H47: 0 | M47: Credit | O47: Manager Reception Food | R47: 0 | U47: red | V47: 12 | W47: 8 | X47: =V47-W47 -> 4 | Z47: =X47*Y47 -> 0
C48: Credit | E48: Water - Front desk | H48: 0 | M48: Credit | O48: Water - Front desk | R48: 0 | X48: total | Z48: =SUM(Z44:Z47) -> 0
C49: Credit | E49: Food to Bar | H49: 0 | M49: Credit | O49: Food to Bar | R49: 0 | X49: credit 28% | Z49: =Z48*0.28 -> 0
C50: Credit | E50: Packages - Sales Promo | H50: 0 | K50: September Lobby Tasting - Wine | M50: Credit | O50: Packages - Sales Promo | R50: 0
C51: Credit | E51: Guest Amenities - Sales Promo | H51: 0 | J51: Date | K51: Amount Used | L51: Cost | M51: Credit | O51: Guest Amenities - Sales Promo | R51: 0 | U51: HH Beer | V51: Original Price | W51: HH Price | X51: Difference | Y51: Sold | Z51: Total
C52: Credit | E52: Employee Meals | H52: 0 | K52: Frenzy x 5 | L52: 48.95 | M52: Credit | O52: Employee Meals | R52: 0 | U52: modelo especial | V52: 7 | W52: 5 | X52: =V52-W52 -> 2 | Z52: =X52*Y52 -> 0
C53: Credit | E53: Café | H53: 0 | M53: Credit | O53: Café | R53: 0 | U53: lonestar | V53: 6 | W53: 5 | X53: =V53-W53 -> 1 | Z53: =X53*Y53 -> 0
C54: Credit | E54: Front Office Amenity | H54: =SUM(L39:L42) -> 0 | M54: Credit | O54: Food Waste | U54: miller lite | V54: 7 | W54: 5 | X54: =V54-W54 -> 2 | Z54: =X54*Y54 -> 0
C55: Credit | E55: H108 Bar Comp | H55: 0 | M55: Credit | O55: H108 Bar Comp | R55: 0 | U55: $2 Lonestar cans | V55: 6 | W55: 2 | X55: =V55-W55 -> 4 | Z55: =X55*Y55 -> 0
C56: Credit | D56: 43150 | E56: Evening Tasting | H56: =L66 -> 48.95 | M56: Credit | O56: Drink Tickets - H137 | X56: total | Z56: =SUM(Z52:Z55) -> 0
C57: Credit | D57: 15% cost | E57: HH Benefit | H57: =Z49 -> 0 | M57: Credit | O57: Amenity - H88 | R57: 0 | X57: credit 25% | Z57: =Z56*0.25 -> 0
C58: Credit | D58: H23 | E58: Sales Amenity | H58: =SUM(L46:L48) -> 170 | M58: Credit | O58: Front Desk | R58: 0
C59: Credit | D59: 30% cost | E59: Wine 1/2 off Promo | H59: =V25 -> 0 | M59: Credit | O59: Other - $5 Green
C60: Credit | E60: Wine Waste | H60: ='Wine Waste'!G71 -> 0 | M60: Credit | O60: Other | R60: 0
C61: Credit | E61: Other - $5 Green | H61: 0 | M61: Credit | O61: Other | R61: 0
C63: Total Credits | I63: =H61+H60+H59+H58+H57+H56+H55+H54+H53+H52+H51+H50+H49+H48+H47+H46+H45+N105 -> 218.95 | M63: Total Credits | S63: =SUM(I63,S20,I20,N105) -> 580.93
C65: Ending Inventory | I65: =Wine!$P$51+'Owners Collection'!$N$9 -> 8823.337 | M65: Ending Inventory | S65: =I65+I22+S22+N107 -> 16572.094
J66: TOTAL | L66: =SUM(L52:L64) -> 48.95
C67: Cost of Bev Consumed | I67: =I36+I41-I63-I65 -> 321.473 | M67: Cost of Bev Consumed | S67: =S36+S41-S63-S65 -> 17486.596
C69: Beverage Cost % | I69: =I67/G34 -> #DIV/0! | M69: Beverage Cost % | S69: =S67/Q34 -> #DIV/0!
I73: Owners Collection
I74: OR Cost Worksheet
I75: Month/Year: | L75: 45986
I76: Gross Beverage Revenue:
I78: Beginning Inventory
I80: Purchases
I81: Petty Cash Purchases
I82: Other Purchases | L82: specs | M82: 0
I83: Total Purchases | N83: =SUM(M80:M82) -> 0
J86: Debit GL Code | M86: Amount
I87: Credit | M87: 0
I88: Credit | M88: 0
I89: Credit | M89: 0
I90: Credit | M90: 0
I91: Credit | M91: 0
I92: Credit | M92: 0
I93: Credit | M93: 0
I94: Credit | M94: 0
I95: Credit | M95: 0
I96: Credit
I97: Credit | M97: 0
I98: Credit
I99: Credit | M99: 0
I100: Credit | J100: 30% cost | K100: Wine 1/2 off Promo | M100: 0
I101: Credit | M101: 0
I102: Credit | M102: 0
I103: Credit | M103: 0
I105: Total Credits | N105: =SUM(M87:M103) -> 0
I107: Ending Inventory
I109: Cost of Bev Consumed | N109: =N78+N83-N105-N107 -> 0
I111: Beverage Cost % | N111: =N109/L76 -> #DIV/0!
